src/keqing/__init__.py
src/keqing/__main__.py
keqing_sword-1.0.0.dist-info/LICENSE
keqing_sword-1.0.0.dist-info/METADATA
keqing_sword-1.0.0.dist-info/WHEEL
keqing_sword-1.0.0.dist-info/RECORD
